LICENSE
MANIFEST.in
README.md
requirements.txt
setup.py
setup_utils.py
deepsense/__init__.py
deepsense/neptune/__init__.py
neptune/__init__.py
neptune/job_wrapper.py
neptune/server.py
neptune/version.py
neptune/generated/__init__.py
neptune/generated/setup.py
neptune/generated/analytics/__init__.py
neptune/generated/analytics/setup.py
neptune/generated/analytics/swagger_client/__init__.py
neptune/generated/analytics/swagger_client/api_client.py
neptune/generated/analytics/swagger_client/configuration.py
neptune/generated/analytics/swagger_client/path_constants.py
neptune/generated/analytics/swagger_client/rest.py
neptune/generated/analytics/swagger_client/apis/__init__.py
neptune/generated/analytics/swagger_client/apis/analyticscontroller_api.py
neptune/generated/analytics/swagger_client/models/__init__.py
neptune/generated/analytics/swagger_client/models/add_user_mapping.py
neptune/generated/analytics/swagger_client/models/anonymous_page_view_event.py
neptune/generated/analytics/swagger_client/models/apply_fee_event.py
neptune/generated/analytics/swagger_client/models/base_enum_model.py
neptune/generated/analytics/swagger_client/models/cancel_account_event.py
neptune/generated/analytics/swagger_client/models/change_credit_card_event.py
neptune/generated/analytics/swagger_client/models/change_pricing_plan_event.py
neptune/generated/analytics/swagger_client/models/cli_usage_event.py
neptune/generated/analytics/swagger_client/models/click_event.py
neptune/generated/analytics/swagger_client/models/contact_email_event.py
neptune/generated/analytics/swagger_client/models/contact_notification_event.py
neptune/generated/analytics/swagger_client/models/contact_us_event.py
neptune/generated/analytics/swagger_client/models/create_account_event.py
neptune/generated/analytics/swagger_client/models/create_project_event.py
neptune/generated/analytics/swagger_client/models/downgrade_event.py
neptune/generated/analytics/swagger_client/models/download_storage_event.py
neptune_cli.egg-info/PKG-INFO
neptune_cli.egg-info/SOURCES.txt
neptune_cli.egg-info/dependency_links.txt
neptune_cli.egg-info/requires.txt
neptune_cli.egg-info/top_level.txt
